LICENSE
MANIFEST.in
README.rst
setup.py
tiny_api/JsonResponse.py
tiny_api/Requests.py
tiny_api/Responses.py
tiny_api/Status.py
tiny_api/__init__.py
tiny_api/api.py
tiny_api/auth.py
tiny_api/constants.py
tiny_api/get_env_var.py
tiny_api/jwt_token.py
tiny_api/middleware.py
tiny_api.egg-info/PKG-INFO
tiny_api.egg-info/SOURCES.txt
tiny_api.egg-info/dependency_links.txt
tiny_api.egg-info/requires.txt
tiny_api.egg-info/top_level.txt