Metadata-Version: 1.2
Name: tiny-api
Version: 0.1.1
Summary: A tiny web framework to create APIs rapidly
Home-page: https://github.com/kaushal-dhungel/tiny-api
Author: Kaushal Dhungel
Author-email: kaushaldhungel01@gmail.com
License: MIT
Download-URL: https://github.com/Kaushal-Dhungel/tiny-api/archive/refs/tags/0.1.1.tar.gz
Keywords: python api,tiny api,python backend api
Platform: UNKNOWN
Classifier: License :: OSI Approved :: MIT License
Classifier: Programming Language :: Python
Classifier: Programming Language :: Python :: 3
Classifier: Programming Language :: Python :: 3.8
Classifier: Programming Language :: Python :: Implementation :: CPython
Classifier: Programming Language :: Python :: Implementation :: PyPy
Classifier: Operating System :: OS Independent
Requires-Python: >=3.6.0
